CHANGES.txt
LICENSE.txt
MANIFEST.in
README.rst
cfontconfig.pxd
factory.pxi
fcmore.h
fontconfig.pxi
fontconfig.pyx
pyproject.toml
setup.cfg
setup.py
Python_fontconfig.egg-info/PKG-INFO
Python_fontconfig.egg-info/SOURCES.txt
Python_fontconfig.egg-info/dependency_links.txt
Python_fontconfig.egg-info/top_level.txt
test/test.py